plugin/__init__.py
plugin/main.py
plugin/utils.py
ultralytics_hub_sdk-0.0.0.dist-info/LICENSE
ultralytics_hub_sdk-0.0.0.dist-info/METADATA
ultralytics_hub_sdk-0.0.0.dist-info/WHEEL
ultralytics_hub_sdk-0.0.0.dist-info/entry_points.txt
ultralytics_hub_sdk-0.0.0.dist-info/top_level.txt
ultralytics_hub_sdk-0.0.0.dist-info/RECORD
