Metadata-Version: 2.1
Name: ultralytics-hub-sdk
Version: 0.0.0
Summary: A placeholder for future Ultralytics projects.
Home-page: https://github.com/ultralytics/pip
Author: Ultralytics
Author-email: hello@ultralytics.com
License: AGPL-3.0
Project-URL: Bug Reports, https://github.com/ultralytics/pip/issues
Project-URL: Funding, https://ultralytics.com
Project-URL: Source, https://github.com/ultralytics/pip
License-File: LICENSE
Requires-Dist: ultralytics >8.0.170
